vba_sync-0.1.5.dist-info/licenses/LICENSE
vbasync/__init__.py
vbasync/cli.py
vba_sync-0.1.5.dist-info/METADATA
vba_sync-0.1.5.dist-info/WHEEL
vba_sync-0.1.5.dist-info/entry_points.txt
vba_sync-0.1.5.dist-info/top_level.txt
vba_sync-0.1.5.dist-info/RECORD
