Metadata-Version: 2.4
Name: vba-sync
Version: 0.1.5
Summary: Export and import VBA macros from Word (.docm .dotm) and Excel (.xlsm .xlam)
Author: "Andrey Kolesov"
Author-email: "never-ya@yandex.ru"
License: MIT
Classifier: Programming Language :: Python :: 3
Classifier: Operating System :: Microsoft :: Windows
Requires-Python: >=3.7
License-File: LICENSE
Requires-Dist: pywin32
Dynamic: license-file
